EA_Toolkit/__init__.py
EA_Toolkit/semi_utils.py
EA_Toolkit/utils.py
EA_Toolkit-0.1.1.dist-info/LICENSE
EA_Toolkit-0.1.1.dist-info/METADATA
EA_Toolkit-0.1.1.dist-info/WHEEL
EA_Toolkit-0.1.1.dist-info/top_level.txt
EA_Toolkit-0.1.1.dist-info/RECORD
