Metadata-Version: 2.1
Name: EA-Toolkit
Version: 0.1.1
Summary: Some Utils for Entity Alignment and GCN.
Author: Cody
Author-email: 615760263@qq.com
Classifier: Programming Language :: Python :: 3
Classifier: License :: OSI Approved :: MIT License
Classifier: Operating System :: OS Independent
Requires-Python: >=3.6
License-File: LICENSE
Requires-Dist: numpy
Requires-Dist: igraph
